nonebot_plugin_internet_outage-0.1.4.dist-info/METADATA
nonebot_plugin_internet_outage-0.1.4.dist-info/WHEEL
nonebot_plugin_internet_outage-0.1.4.dist-info/entry_points.txt
nonebot_plugin_internet_outage-0.1.4.dist-info/licenses/LICENSE
nonebot_plugin_internet_outage/__init__.py
nonebot_plugin_internet_outage-0.1.4.dist-info/RECORD
