Metadata-Version: 2.1
Name: nonebot-plugin-internet-outage
Version: 0.1.4
Summary: NoneBot2 plugin for monitoring global internet outages based on Cloudflare Radar
Author-Email: CN171-1 <CN171_11_@outlook.com>
License: MIT
Project-URL: Homepage, https://github.com/CN171-1/nonebot-plugin-internet-outage
Project-URL: Repository, https://github.com/CN171-1/nonebot-plugin-internet-outage
Requires-Python: >=3.9
Requires-Dist: nonebot2<3.0.0,>=2.3.0
Requires-Dist: nonebot-adapter-onebot>=2.1.5
Requires-Dist: nonebot-plugin-apscheduler>=0.2.0
Requires-Dist: nonebot-plugin-localstore>=0.6.0
Requires-Dist: httpx>=0.28.0
